distem/__init__.py
distem-0.0.5.dist-info/LICENSE.txt
distem-0.0.5.dist-info/METADATA
distem-0.0.5.dist-info/WHEEL
distem-0.0.5.dist-info/entry_points.txt
distem-0.0.5.dist-info/top_level.txt
distem-0.0.5.dist-info/RECORD
